[
    {
        "start": 417125,
        "end": 423798,
        "end_index": 421629,
        "fr": {
            "qoute": "Ça sert à rien de mettre d'autres lampes. Arrête ton délire ! Arrête ! Il a disparu, tu entends ? "
        },
        "qoute": "You don't need more lamps. You need to stop this, okay? He is just lost."
    },
    {
        "start": 493409,
        "end": 497747,
        "end_index": 494494,
        "fr": {
            "qoute": "Il existe pas. Mais si on croise une créature, je la viserai en pleine tête. "
        },
        "qoute": "It's made up. But if there is something out there, I'm gonna shoot it in the eye."
    },
    {
        "start": 516349,
        "end": 521062,
        "end_index": 518935,
        "fr": {
            "qoute": "Il faut prendre des forces pour notre mission. Des armes, ça sert à quoi, les gars ? "
        },
        "qoute": "We need energy for our travels. For stamina. And besides, why do we even need weapons anyway?"
    },
    {
        "start": 521145,
        "end": 527777,
        "end_index": 525107,
        "fr": {
            "qoute": " On a Elfe. Elle a juste fermé une porte ! Avec sa pensée ! Tu te rends compte ? C'est du délire ! "
        },
        "qoute": "We have her. She shut one door! With her mind! Are you kidding me? That's insane!"
    },
    {
        "start": 527860,
        "end": 536452,
        "end_index": 532782,
        "fr": {
            "qoute": "Imagine les autres trucs cool qu'elle pourrait faire ? Genre… Je parie qu'elle arriverait à faire voler ce vaisseau. "
        },
        "qoute": "Imagine all the other cool stuff she could do. Like. I bet. that she could make this fly!"
    },
    {
        "start": 1849722,
        "end": 1855770,
        "end_index": 1853726,
        "fr": {
            "qoute": " Vous en faites, une tête.  Le mannequin vedette. Quoi ? Ce taré nous a espionnés hier soir. "
        },
        "qoute": "What's going on? Here's the starring lady. What? This creep was spying on us last night."
    }
]