{
    "What": "무엇",
    "If": "만약",
    "See": "보다",
    "Other": "다른",
    "Outsmart": "똑똑하게 이긴다",
    "Bad": "나쁜",
    "Guys": "사람들",
    "Most": "대부분",
    "Time": "시간",
    "Totally": "완전히",
    "But": "그러나",
    "Sometimes": "가끔",
    "Smart": "똑똑한",
    "Too": "너무",
    "Know": "알다",
    "Needs": "필요로 하다",
    "Fireballs": "화염구",
    "questions": "질문들",
    "Cosmos": "코스모스",
    "Carl Sagan": "칼 사건",
    "dimensions": "차원",
    "beyond": "저 너머에",
    "theoretically": "이론적으로",
    "travel": "여행하다, 이동하다",
    "upside down": "뒤집힌 상태, 거꾸로",
    "acrobat": "공중곡예사",
    "get to": "도착하다, 이르다"
}